{"total":101,"pageSize":10,"pageCount":11,"data":[{"title":"在 Hexo 中插入 AntV 动态图表","slug":"hexo-tag-antv","date":"2017-11-30T02:53:24.000Z","updated":"2018-04-19T14:55:25.957Z","comments":true,"path":"api/articles/hexo-tag-antv.json","excerpt":null,"keywords":null,"cover":null,"content":null,"raw":null,"categories":[{"name":"前端技术","path":"api/categories/前端技术.json"}],"tags":[{"name":"Hexo","path":"api/tags/Hexo.json"},{"name":"AntV","path":"api/tags/AntV.json"},{"name":"hexo-tag-antv","path":"api/tags/hexo-tag-antv.json"}]},{"title":"《Java编程思想》读书笔记（三）","slug":"《Java编程思想》读书笔记（三）","date":"2017-11-28T13:15:08.000Z","updated":"2018-04-19T14:55:25.957Z","comments":true,"path":"api/articles/《Java编程思想》读书笔记（三）.json","excerpt":null,"keywords":null,"cover":"https://img.wshunli.com/Java/Java编程思想/访问控制.png-hexo.png","content":null,"raw":null,"categories":[{"name":"移动端技术","path":"api/categories/移动端技术.json"}],"tags":[{"name":"Java","path":"api/tags/Java.json"},{"name":"读书笔记","path":"api/tags/读书笔记.json"},{"name":"《Java编程思想》","path":"api/tags/《Java编程思想》.json"}]},{"title":"《Java编程思想》读书笔记（二）","slug":"《Java编程思想》读书笔记（二）","date":"2017-11-28T12:47:30.000Z","updated":"2018-04-19T14:55:25.957Z","comments":true,"path":"api/articles/《Java编程思想》读书笔记（二）.json","excerpt":null,"keywords":null,"cover":null,"content":null,"raw":null,"categories":[{"name":"移动端技术","path":"api/categories/移动端技术.json"}],"tags":[{"name":"Java","path":"api/tags/Java.json"},{"name":"读书笔记","path":"api/tags/读书笔记.json"},{"name":"《Java编程思想》","path":"api/tags/《Java编程思想》.json"}]},{"title":"《Java编程思想》读书笔记（一）","slug":"《Java编程思想》读书笔记（一）","date":"2017-11-28T02:58:36.000Z","updated":"2018-04-19T14:55:25.957Z","comments":true,"path":"api/articles/《Java编程思想》读书笔记（一）.json","excerpt":null,"keywords":null,"cover":null,"content":null,"raw":null,"categories":[{"name":"移动端技术","path":"api/categories/移动端技术.json"}],"tags":[{"name":"Java","path":"api/tags/Java.json"},{"name":"读书笔记","path":"api/tags/读书笔记.json"},{"name":"《Java编程思想》","path":"api/tags/《Java编程思想》.json"}]},{"title":"沉迷学术，不可自拔（四）","slug":"沉迷学术，不可自拔（四）","date":"2017-11-19T06:34:43.000Z","updated":"2018-04-19T14:55:25.957Z","comments":true,"path":"api/articles/沉迷学术，不可自拔（四）.json","excerpt":null,"keywords":null,"cover":null,"content":null,"raw":null,"categories":[{"name":"沉迷学术","path":"api/categories/沉迷学术.json"}],"tags":[{"name":"沉迷学术","path":"api/tags/沉迷学术.json"},{"name":"胡思乱想","path":"api/tags/胡思乱想.json"}]},{"title":"《React Native开发指南》读书笔记（一）","slug":"《React-Native开发指南》读书笔记（一）","date":"2017-11-18T04:23:39.000Z","updated":"2018-04-19T14:55:25.957Z","comments":true,"path":"api/articles/《React-Native开发指南》读书笔记（一）.json","excerpt":null,"keywords":null,"cover":null,"content":null,"raw":null,"categories":[{"name":"跨平台技术","path":"api/categories/跨平台技术.json"}],"tags":[{"name":"读书笔记","path":"api/tags/读书笔记.json"},{"name":"React Native","path":"api/tags/React Native.json"},{"name":"《React Native开发指南》","path":"api/tags/《React Native开发指南》.json"}]},{"title":"《深入浅出React和Redux》读书笔记（二）","slug":"《深入浅出React和Redux》读书笔记（二）","date":"2017-11-15T08:05:27.000Z","updated":"2018-04-19T14:55:25.957Z","comments":true,"path":"api/articles/《深入浅出React和Redux》读书笔记（二）.json","excerpt":null,"keywords":null,"cover":"https://img.wshunli.com/React/深入浅出React和Redux/MVC.png-hexo.png","content":null,"raw":null,"categories":[{"name":"前端技术","path":"api/categories/前端技术.json"}],"tags":[{"name":"读书笔记","path":"api/tags/读书笔记.json"},{"name":"React","path":"api/tags/React.json"},{"name":"《深入浅出React和Redux》","path":"api/tags/《深入浅出React和Redux》.json"}]},{"title":"又拍云CDN全站加速","slug":"又拍云CDN全站加速","date":"2017-11-11T11:44:24.000Z","updated":"2018-04-19T14:55:25.957Z","comments":true,"path":"api/articles/又拍云CDN全站加速.json","excerpt":null,"keywords":null,"cover":null,"content":null,"raw":null,"categories":[{"name":"博客维护","path":"api/categories/博客维护.json"}],"tags":[{"name":"Hexo","path":"api/tags/Hexo.json"},{"name":"Upyun","path":"api/tags/Upyun.json"}]},{"title":"《深入浅出React和Redux》读书笔记（一）","slug":"《深入浅出React和Redux》读书笔记（一）","date":"2017-11-10T05:40:03.000Z","updated":"2018-04-19T14:55:25.957Z","comments":true,"path":"api/articles/《深入浅出React和Redux》读书笔记（一）.json","excerpt":null,"keywords":null,"cover":"https://img.wshunli.com/React/深入浅出React和Redux/React技术栈.png-hexo.png","content":null,"raw":null,"categories":[{"name":"前端技术","path":"api/categories/前端技术.json"}],"tags":[{"name":"读书笔记","path":"api/tags/读书笔记.json"},{"name":"React","path":"api/tags/React.json"},{"name":"《深入浅出React和Redux》","path":"api/tags/《深入浅出React和Redux》.json"}]},{"title":"使用Travis CI自动部署Hexo博客","slug":"使用Travis-CI自动部署Hexo博客","date":"2017-11-09T11:14:08.000Z","updated":"2018-04-19T14:55:25.957Z","comments":true,"path":"api/articles/使用Travis-CI自动部署Hexo博客.json","excerpt":null,"keywords":null,"cover":"https://img.wshunli.com/使用TravisCI自动部署Hexo博客/TravisCI-Hexo1.png","content":null,"raw":null,"categories":[{"name":"博客维护","path":"api/categories/博客维护.json"}],"tags":[{"name":"Hexo","path":"api/tags/Hexo.json"},{"name":"TravisCI","path":"api/tags/TravisCI.json"}]}]}